jupyter_aichat/__init__.py
jupyter_aichat/aichat_magic.py
jupyter_aichat/api_types.py
jupyter_aichat/authentication.py
jupyter_aichat/client.py
jupyter_aichat/output.py
jupyter_aichat/tokens.py
jupyter_aichat/data/account_and_key.md
jupyter_aichat/data/authentication_note.md
jupyter_aichat/data/commands.md
jupyter_aichat/data/help.md
jupyter_aichat/data/help_assistant_system_message.md
jupyter_aichat/data/internals.md
jupyter_aichat/data/load_ipython_extension.md
jupyter_aichat/data/pricing.md
jupyter_aichat-0.0.3.dist-info/LICENSE
jupyter_aichat-0.0.3.dist-info/WHEEL
jupyter_aichat-0.0.3.dist-info/METADATA
jupyter_aichat-0.0.3.dist-info/RECORD
