Metadata-Version: 2.1
Name: jupyter_aichat
Version: 0.0.3
Summary: Jupyter magic command for having AI chat conversations in a notebook
Author-email: Antti Kaihola <13725+akaihola@users.noreply.github.com>
Requires-Dist: IPython
Requires-Dist: openai
Requires-Dist: setuptools
Requires-Dist: tiktoken
Project-URL: Home, https://github.com/akaihola/jupyter_aichat
